IsNetHelper/IsNetHelper.py
IsNetHelper/QNBFaturaCreator.py
IsNetHelper/__init__.py
IsNetHelper/models/Request.py
IsNetHelper/models/__init__.py
IsNetHelper/utils/__init__.py
IsNetHelper/utils/utils.py
isnet_helper-1.0.1.dist-info/METADATA
isnet_helper-1.0.1.dist-info/WHEEL
isnet_helper-1.0.1.dist-info/top_level.txt
isnet_helper-1.0.1.dist-info/RECORD
