Metadata-Version: 2.1
Name: isnet-helper
Version: 1.0.1
Summary: Isnet Helper
Author: Esat Yılmaz
Author-email: esatyilmaz3500@gmail.com
Classifier: Programming Language :: Python :: 3.9
Classifier: License :: OSI Approved :: MIT License
Classifier: Operating System :: OS Independent
Requires-Python: >=3.9
Requires-Dist: pydantic
Requires-Dist: requests
Requires-Dist: zeep
